{
  "code": 200,
  "status": "OK",
  "message": "Request has been successfully processed.",
  "data": [
    {
      "type": "village",
      "code": "15.03.07.2001",
      "name": "LUBUK JERING",
      "provinceCode": "15",
      "provinceName": "JAMBI",
      "cityCode": "15.03",
      "cityName": "KAB. SAROLANGUN",
      "districtCode": "15.03.07",
      "districtName": "AIR HITAM",
      "indonesiaTimezone": "WIB",
      "ianaTimezone": "Asia/Jakarta",
      "timezoneOffset": "+07:00",
      "postalCode": 37490,
      "coordinate": {
        "longitude": 102.6342534,
        "latitude": -1.9626256,
        "elevation": 57
      }
    },
    {
      "type": "village",
      "code": "15.03.07.2002",
      "name": "JERNIH",
      "provinceCode": "15",
      "provinceName": "JAMBI",
      "cityCode": "15.03",
      "cityName": "KAB. SAROLANGUN",
      "districtCode": "15.03.07",
      "districtName": "AIR HITAM",
      "indonesiaTimezone": "WIB",
      "ianaTimezone": "Asia/Jakarta",
      "timezoneOffset": "+07:00",
      "postalCode": 37490,
      "coordinate": {
        "longitude": 102.68274,
        "latitude": -2.0093486,
        "elevation": 37
      }
    },
    {
      "type": "village",
      "code": "15.03.07.2003",
      "name": "DESA BARU",
      "provinceCode": "15",
      "provinceName": "JAMBI",
      "cityCode": "15.03",
      "cityName": "KAB. SAROLANGUN",
      "districtCode": "15.03.07",
      "districtName": "AIR HITAM",
      "indonesiaTimezone": "WIB",
      "ianaTimezone": "Asia/Jakarta",
      "timezoneOffset": "+07:00",
      "postalCode": 28452,
      "coordinate": {
        "longitude": 101.5237244,
        "latitude": 0.4303128,
        "elevation": 15
      }
    },
    {
      "type": "village",
      "code": "15.03.07.2004",
      "name": "SEMURUNG",
      "provinceCode": "15",
      "provinceName": "JAMBI",
      "cityCode": "15.03",
      "cityName": "KAB. SAROLANGUN",
      "districtCode": "15.03.07",
      "districtName": "AIR HITAM",
      "indonesiaTimezone": "WIB",
      "ianaTimezone": "Asia/Jakarta",
      "timezoneOffset": "+07:00",
      "postalCode": 37490,
      "coordinate": {
        "longitude": 102.7276172,
        "latitude": -2.0358494,
        "elevation": 41
      }
    },
    {
      "type": "village",
      "code": "15.03.07.2005",
      "name": "LUBUK KEPAYANG",
      "provinceCode": "15",
      "provinceName": "JAMBI",
      "cityCode": "15.03",
      "cityName": "KAB. SAROLANGUN",
      "districtCode": "15.03.07",
      "districtName": "AIR HITAM",
      "indonesiaTimezone": "WIB",
      "ianaTimezone": "Asia/Jakarta",
      "timezoneOffset": "+07:00",
      "postalCode": 31471,
      "coordinate": {
        "longitude": 103.5979867,
        "latitude": -3.7699068,
        "elevation": 87
      }
    },
    {
      "type": "village",
      "code": "15.03.07.2006",
      "name": "PEMATANG KABAU",
      "provinceCode": "15",
      "provinceName": "JAMBI",
      "cityCode": "15.03",
      "cityName": "KAB. SAROLANGUN",
      "districtCode": "15.03.07",
      "districtName": "AIR HITAM",
      "indonesiaTimezone": "WIB",
      "ianaTimezone": "Asia/Jakarta",
      "timezoneOffset": "+07:00",
      "postalCode": 37490,
      "coordinate": {
        "longitude": 102.6011621,
        "latitude": -1.965472,
        "elevation": 51
      }
    },
    {
      "type": "village",
      "code": "15.03.07.2007",
      "name": "BUKIT SUBAN",
      "provinceCode": "15",
      "provinceName": "JAMBI",
      "cityCode": "15.03",
      "cityName": "KAB. SAROLANGUN",
      "districtCode": "15.03.07",
      "districtName": "AIR HITAM",
      "indonesiaTimezone": "WIB",
      "ianaTimezone": "Asia/Jakarta",
      "timezoneOffset": "+07:00",
      "postalCode": 37490,
      "coordinate": {
        "longitude": 102.5110191,
        "latitude": -1.9650054,
        "elevation": 53
      }
    },
    {
      "type": "village",
      "code": "15.03.07.2008",
      "name": "MENTAWAK BARU",
      "provinceCode": "15",
      "provinceName": "JAMBI",
      "cityCode": "15.03",
      "cityName": "KAB. SAROLANGUN",
      "districtCode": "15.03.07",
      "districtName": "AIR HITAM",
      "indonesiaTimezone": "WIB",
      "ianaTimezone": "Asia/Jakarta",
      "timezoneOffset": "+07:00",
      "postalCode": 37490,
      "coordinate": {
        "longitude": 102.5611228,
        "latitude": -2.0237732,
        "elevation": 45
      }
    },
    {
      "type": "village",
      "code": "15.03.07.2009",
      "name": "MENTAWAK ULU",
      "provinceCode": "15",
      "provinceName": "JAMBI",
      "cityCode": "15.03",
      "cityName": "KAB. SAROLANGUN",
      "districtCode": "15.03.07",
      "districtName": "AIR HITAM",
      "indonesiaTimezone": "WIB",
      "ianaTimezone": "Asia/Jakarta",
      "timezoneOffset": "+07:00",
      "postalCode": 37490,
      "coordinate": {
        "longitude": 102.5696812,
        "latitude": -2.0746061,
        "elevation": 55
      }
    }
  ],
  "metadata": {
    "totalRow": 9
  }
}