{
  "code": 200,
  "status": "OK",
  "message": "Request has been successfully processed.",
  "data": [
    {
      "type": "village",
      "code": "65.04.01.2001",
      "name": "TIDENG PALE",
      "provinceCode": "65",
      "provinceName": "KALIMANTAN UTARA",
      "cityCode": "65.04",
      "cityName": "KAB. TANA TIDUNG",
      "districtCode": "65.04.01",
      "districtName": "SESAYAP",
      "indonesiaTimezone": "WITA",
      "ianaTimezone": "Asia/Makassar",
      "timezoneOffset": "+08:00",
      "postalCode": 77151,
      "coordinate": {
        "longitude": 116.9112246,
        "latitude": 3.6379219,
        "elevation": 2
      }
    },
    {
      "type": "village",
      "code": "65.04.01.2002",
      "name": "LIMBU SEDULUN",
      "provinceCode": "65",
      "provinceName": "KALIMANTAN UTARA",
      "cityCode": "65.04",
      "cityName": "KAB. TANA TIDUNG",
      "districtCode": "65.04.01",
      "districtName": "SESAYAP",
      "indonesiaTimezone": "WITA",
      "ianaTimezone": "Asia/Makassar",
      "timezoneOffset": "+08:00",
      "postalCode": 77151,
      "coordinate": {
        "longitude": 116.8959804,
        "latitude": 3.5504985,
        "elevation": 11
      }
    },
    {
      "type": "village",
      "code": "65.04.01.2003",
      "name": "SEBIDAI",
      "provinceCode": "65",
      "provinceName": "KALIMANTAN UTARA",
      "cityCode": "65.04",
      "cityName": "KAB. TANA TIDUNG",
      "districtCode": "65.04.01",
      "districtName": "SESAYAP",
      "indonesiaTimezone": "WITA",
      "ianaTimezone": "Asia/Makassar",
      "timezoneOffset": "+08:00",
      "postalCode": 77151,
      "coordinate": {
        "longitude": 116.9375807,
        "latitude": 3.5469701,
        "elevation": 37
      }
    },
    {
      "type": "village",
      "code": "65.04.01.2004",
      "name": "SEDULUN",
      "provinceCode": "65",
      "provinceName": "KALIMANTAN UTARA",
      "cityCode": "65.04",
      "cityName": "KAB. TANA TIDUNG",
      "districtCode": "65.04.01",
      "districtName": "SESAYAP",
      "indonesiaTimezone": "WITA",
      "ianaTimezone": "Asia/Makassar",
      "timezoneOffset": "+08:00",
      "postalCode": 77151,
      "coordinate": {
        "longitude": 116.871146,
        "latitude": 3.565378,
        "elevation": 19
      }
    },
    {
      "type": "village",
      "code": "65.04.01.2005",
      "name": "TIDENG PALE TIMUR",
      "provinceCode": "65",
      "provinceName": "KALIMANTAN UTARA",
      "cityCode": "65.04",
      "cityName": "KAB. TANA TIDUNG",
      "districtCode": "65.04.01",
      "districtName": "SESAYAP",
      "indonesiaTimezone": "WITA",
      "ianaTimezone": "Asia/Makassar",
      "timezoneOffset": "+08:00",
      "postalCode": 77151,
      "coordinate": {
        "longitude": 116.9313359,
        "latitude": 3.6279468,
        "elevation": 21
      }
    },
    {
      "type": "village",
      "code": "65.04.01.2006",
      "name": "GUNAWAN",
      "provinceCode": "65",
      "provinceName": "KALIMANTAN UTARA",
      "cityCode": "65.04",
      "cityName": "KAB. TANA TIDUNG",
      "districtCode": "65.04.01",
      "districtName": "SESAYAP",
      "indonesiaTimezone": "WITA",
      "ianaTimezone": "Asia/Makassar",
      "timezoneOffset": "+08:00",
      "postalCode": 77151,
      "coordinate": {
        "longitude": 116.9174814,
        "latitude": 3.5350137,
        "elevation": 51
      }
    },
    {
      "type": "village",
      "code": "65.04.01.2007",
      "name": "SEBAWANG",
      "provinceCode": "65",
      "provinceName": "KALIMANTAN UTARA",
      "cityCode": "65.04",
      "cityName": "KAB. TANA TIDUNG",
      "districtCode": "65.04.01",
      "districtName": "SESAYAP",
      "indonesiaTimezone": "WITA",
      "ianaTimezone": "Asia/Makassar",
      "timezoneOffset": "+08:00",
      "postalCode": 77151,
      "coordinate": {
        "longitude": 116.9542099,
        "latitude": 3.547044,
        "elevation": 42
      }
    }
  ],
  "metadata": {
    "totalRow": 7
  }
}