{
  "code": 200,
  "status": "OK",
  "message": "Request has been successfully processed.",
  "data": [
    {
      "type": "village",
      "code": "74.71.09.1001",
      "name": "PUUWATU",
      "provinceCode": "74",
      "provinceName": "SULAWESI TENGGARA",
      "cityCode": "74.71",
      "cityName": "KOTA KENDARI",
      "districtCode": "74.71.09",
      "districtName": "PUUWATU",
      "indonesiaTimezone": "WITA",
      "ianaTimezone": "Asia/Makassar",
      "timezoneOffset": "+08:00",
      "postalCode": 93114,
      "coordinate": {
        "longitude": 122.4633641,
        "latitude": -3.9685537,
        "elevation": 44
      }
    },
    {
      "type": "village",
      "code": "74.71.09.1002",
      "name": "WATULONDO",
      "provinceCode": "74",
      "provinceName": "SULAWESI TENGGARA",
      "cityCode": "74.71",
      "cityName": "KOTA KENDARI",
      "districtCode": "74.71.09",
      "districtName": "PUUWATU",
      "indonesiaTimezone": "WITA",
      "ianaTimezone": "Asia/Makassar",
      "timezoneOffset": "+08:00",
      "postalCode": 93114,
      "coordinate": {
        "longitude": 122.4773984,
        "latitude": -3.9722987,
        "elevation": 33
      }
    },
    {
      "type": "village",
      "code": "74.71.09.1003",
      "name": "PUNGGOLAKA",
      "provinceCode": "74",
      "provinceName": "SULAWESI TENGGARA",
      "cityCode": "74.71",
      "cityName": "KOTA KENDARI",
      "districtCode": "74.71.09",
      "districtName": "PUUWATU",
      "indonesiaTimezone": "WITA",
      "ianaTimezone": "Asia/Makassar",
      "timezoneOffset": "+08:00",
      "postalCode": 93115,
      "coordinate": {
        "longitude": 122.4963758,
        "latitude": -3.96715,
        "elevation": 25
      }
    },
    {
      "type": "village",
      "code": "74.71.09.1004",
      "name": "TOBUUHA",
      "provinceCode": "74",
      "provinceName": "SULAWESI TENGGARA",
      "cityCode": "74.71",
      "cityName": "KOTA KENDARI",
      "districtCode": "74.71.09",
      "districtName": "PUUWATU",
      "indonesiaTimezone": "WITA",
      "ianaTimezone": "Asia/Makassar",
      "timezoneOffset": "+08:00",
      "postalCode": 93115,
      "coordinate": {
        "longitude": 122.5055284,
        "latitude": -3.9647729,
        "elevation": 31
      }
    },
    {
      "type": "village",
      "code": "74.71.09.1005",
      "name": "ABELI DALAM",
      "provinceCode": "74",
      "provinceName": "SULAWESI TENGGARA",
      "cityCode": "74.71",
      "cityName": "KOTA KENDARI",
      "districtCode": "74.71.09",
      "districtName": "PUUWATU",
      "indonesiaTimezone": "WITA",
      "ianaTimezone": "Asia/Makassar",
      "timezoneOffset": "+08:00",
      "postalCode": 93115,
      "coordinate": {
        "longitude": 122.4539372,
        "latitude": -3.9993744,
        "elevation": 81
      }
    },
    {
      "type": "village",
      "code": "74.71.09.1006",
      "name": "LALODATI",
      "provinceCode": "74",
      "provinceName": "SULAWESI TENGGARA",
      "cityCode": "74.71",
      "cityName": "KOTA KENDARI",
      "districtCode": "74.71.09",
      "districtName": "PUUWATU",
      "indonesiaTimezone": "WITA",
      "ianaTimezone": "Asia/Makassar",
      "timezoneOffset": "+08:00",
      "postalCode": 93115,
      "coordinate": {
        "longitude": 122.4825745,
        "latitude": -3.9380983,
        "elevation": 38
      }
    }
  ],
  "metadata": {
    "totalRow": 6
  }
}