{
  "code": 200,
  "status": "OK",
  "message": "Request has been successfully processed.",
  "data": [
    {
      "type": "district",
      "code": "71.01.05",
      "name": "SANG TOMBOLANG",
      "provinceCode": "71",
      "provinceName": "SULAWESI UTARA",
      "cityCode": "71.01",
      "cityName": "KAB. BOLAANG MONGONDOW"
    },
    {
      "type": "district",
      "code": "71.01.09",
      "name": "DUMOGA BARAT",
      "provinceCode": "71",
      "provinceName": "SULAWESI UTARA",
      "cityCode": "71.01",
      "cityName": "KAB. BOLAANG MONGONDOW"
    },
    {
      "type": "district",
      "code": "71.01.10",
      "name": "DUMOGA TIMUR",
      "provinceCode": "71",
      "provinceName": "SULAWESI UTARA",
      "cityCode": "71.01",
      "cityName": "KAB. BOLAANG MONGONDOW"
    },
    {
      "type": "district",
      "code": "71.01.11",
      "name": "DUMOGA UTARA",
      "provinceCode": "71",
      "provinceName": "SULAWESI UTARA",
      "cityCode": "71.01",
      "cityName": "KAB. BOLAANG MONGONDOW"
    },
    {
      "type": "district",
      "code": "71.01.12",
      "name": "LOLAK",
      "provinceCode": "71",
      "provinceName": "SULAWESI UTARA",
      "cityCode": "71.01",
      "cityName": "KAB. BOLAANG MONGONDOW"
    },
    {
      "type": "district",
      "code": "71.01.13",
      "name": "BOLAANG",
      "provinceCode": "71",
      "provinceName": "SULAWESI UTARA",
      "cityCode": "71.01",
      "cityName": "KAB. BOLAANG MONGONDOW"
    },
    {
      "type": "district",
      "code": "71.01.14",
      "name": "LOLAYAN",
      "provinceCode": "71",
      "provinceName": "SULAWESI UTARA",
      "cityCode": "71.01",
      "cityName": "KAB. BOLAANG MONGONDOW"
    },
    {
      "type": "district",
      "code": "71.01.19",
      "name": "PASSI BARAT",
      "provinceCode": "71",
      "provinceName": "SULAWESI UTARA",
      "cityCode": "71.01",
      "cityName": "KAB. BOLAANG MONGONDOW"
    },
    {
      "type": "district",
      "code": "71.01.20",
      "name": "POIGAR",
      "provinceCode": "71",
      "provinceName": "SULAWESI UTARA",
      "cityCode": "71.01",
      "cityName": "KAB. BOLAANG MONGONDOW"
    },
    {
      "type": "district",
      "code": "71.01.22",
      "name": "PASSI TIMUR",
      "provinceCode": "71",
      "provinceName": "SULAWESI UTARA",
      "cityCode": "71.01",
      "cityName": "KAB. BOLAANG MONGONDOW"
    },
    {
      "type": "district",
      "code": "71.01.31",
      "name": "BOLAANG TIMUR",
      "provinceCode": "71",
      "provinceName": "SULAWESI UTARA",
      "cityCode": "71.01",
      "cityName": "KAB. BOLAANG MONGONDOW"
    },
    {
      "type": "district",
      "code": "71.01.32",
      "name": "BILALANG",
      "provinceCode": "71",
      "provinceName": "SULAWESI UTARA",
      "cityCode": "71.01",
      "cityName": "KAB. BOLAANG MONGONDOW"
    },
    {
      "type": "district",
      "code": "71.01.33",
      "name": "DUMOGA",
      "provinceCode": "71",
      "provinceName": "SULAWESI UTARA",
      "cityCode": "71.01",
      "cityName": "KAB. BOLAANG MONGONDOW"
    },
    {
      "type": "district",
      "code": "71.01.34",
      "name": "DUMOGA TENGGARA",
      "provinceCode": "71",
      "provinceName": "SULAWESI UTARA",
      "cityCode": "71.01",
      "cityName": "KAB. BOLAANG MONGONDOW"
    },
    {
      "type": "district",
      "code": "71.01.35",
      "name": "DUMOGA TENGAH",
      "provinceCode": "71",
      "provinceName": "SULAWESI UTARA",
      "cityCode": "71.01",
      "cityName": "KAB. BOLAANG MONGONDOW"
    }
  ],
  "metadata": {
    "totalRow": 15
  }
}